pyballistics/__init__.py
pyballistics/gpowders_si.csv
pyballistics/lagrange.c
pyballistics/lagrange.cp312-win_amd64.pyd
pyballistics/lagrange.pxd
pyballistics/lagrange.pyx
pyballistics/options.py
pyballistics/termalconduct.c
pyballistics/termalconduct.cp312-win_amd64.pyd
pyballistics/termalconduct.pxd
pyballistics/termalconduct.pyx
pyballistics/termo.c
pyballistics/termo.cp312-win_amd64.pyd
pyballistics/termo.pxd
pyballistics/termo.pyx
pyballistics-1.1.3.dist-info/LICENSE.txt
pyballistics-1.1.3.dist-info/METADATA
pyballistics-1.1.3.dist-info/WHEEL
pyballistics-1.1.3.dist-info/top_level.txt
pyballistics-1.1.3.dist-info/RECORD
